napalm_asa/_SUPPORTED_INTERFACES_ENDPOINTS.py
napalm_asa/__init__.py
napalm_asa/asa.py
napalm_asa/constants.py
napalm_asa/utils/__init__.py
napalm_asa-0.1.4.dist-info/LICENSE
napalm_asa-0.1.4.dist-info/METADATA
napalm_asa-0.1.4.dist-info/WHEEL
napalm_asa-0.1.4.dist-info/top_level.txt
napalm_asa-0.1.4.dist-info/RECORD
