Metadata-Version: 2.1
Name: napalm-asa
Version: 0.1.4
Summary: Cisco ASA driver for NAPALM
Home-page: https://github.com/napalm-automation-community/napalm-asa
Author: Diogo Assumpcao
Author-email: daa@hey.com
License: UNKNOWN
Platform: UNKNOWN
Classifier: Topic :: Utilities
Classifier: Programming Language :: Python
Classifier: Programming Language :: Python :: 3
Classifier: Programming Language :: Python :: 3.8
Classifier: Operating System :: POSIX :: Linux
Classifier: Operating System :: MacOS
